{
  "seller": {
    "name": "OVH HISPANO S.L.",
    "vat_id": "B83834747",
    "address": {
      "postcode": "28014",
      "street": "C/ Alcalá 21, 5ª planta",
      "city": "Madrid",
      "country": "ES",
      "europe": "Y"
    }
  },
  "invoice_number": "ES3924835",
  "invoice_date": "2025-07-10",
  "currency": "EUR",
  "amount": 0.0,
  "vat_amount": 0.0,
  "withholding_tax_amount": 0.0,
  "line_items": [
    {
      "description": "Zimbra Starter monthly pricing Del 10-07-2025 al 09-08-2025 (Referencia: 1c4b3c5a-e378-4de4-a3f3-25344eb14ccd)",
      "quantity": 1,
      "unit_price": 0.3,
      "vat_rate": 21.0,
      "price_includes_vat": false,
      "withholding_tax_rate": 0.0
    },
    {
      "description": "Free starter account with domain Del 10-07-2025 al 09-08-2025 (Referencia: 1c4b3c5a-e378-4de4-a3f3-25344eb14ccd)",
      "quantity": 1,
      "unit_price": -0.3,
      "vat_rate": 0.0,
      "price_includes_vat": false,
      "withholding_tax_rate": 0.0
    }
  ],
  "buyer": {
    "name": "Zhintek Consultoria Tencologica SL",
    "vat_id": "ESB65779282",
    "address": {
      "postcode": "25700",
      "street": "c/ de la Sort 11, 1r",
      "city": "La Seu d'Urgell",
      "country": "ES",
      "europe": "Y"
    }
  }
}